TLogger4/TLogger4.py
TLogger4/__init__.py
tlogger4-1.0.dist-info/licenses/LICENSE
tlogger4-1.0.dist-info/METADATA
tlogger4-1.0.dist-info/WHEEL
tlogger4-1.0.dist-info/top_level.txt
tlogger4-1.0.dist-info/RECORD
