Metadata-Version: 2.4
Name: TLogger4
Version: 1.0
Summary: Colored logger with console/file output
Home-page: https://github.com/yrzd6
Author: Yrzd6
Author-email: 
License: MPL-2.0
Classifier: Programming Language :: Python :: 3 :: Only
Classifier: License :: OSI Approved :: Mozilla Public License 2.0 (MPL 2.0)
Classifier: Operating System :: Microsoft :: Windows
Classifier: Development Status :: 4 - Beta
Classifier: Topic :: Utilities
Requires-Python: >=3.10
License-File: LICENSE
Dynamic: author
Dynamic: classifier
Dynamic: description
Dynamic: description-content-type
Dynamic: home-page
Dynamic: license
Dynamic: license-file
Dynamic: requires-python
Dynamic: summary
